{
	"animations": [
		{
			"loop": false,
			"offsets": [
				98,
				3
			],
			"anim": "singDOWN",
			"fps": 24,
			"name": "down",
			"indices": []
		},
		{
			"loop": false,
			"offsets": [
				-5,
				0
			],
			"anim": "idle",
			"fps": 24,
			"name": "idle",
			"indices": []
		},
		{
			"offsets": [
				86,
				0
			],
			"loop": false,
			"fps": 24,
			"anim": "singRIGHT",
			"indices": [],
			"name": "right"
		},
		{
			"offsets": [
				124,
				136
			],
			"loop": false,
			"fps": 24,
			"anim": "singUP",
			"indices": [],
			"name": "up"
		},
		{
			"offsets": [
				105,
				0
			],
			"loop": false,
			"fps": 24,
			"anim": "singLEFT",
			"indices": [],
			"name": "left"
		}
	],
	"no_antialiasing": false,
	"image": "characters/sonic_nmi",
	"position": [
		96,
		260
	],
	"healthicon": "nmi",
	"flip_x": false,
	"healthbar_colors": [
		255,
		255,
		255
	],
	"camera_position": [
		-80,
		40
	],
	"sing_duration": 5.99999999999999,
	"scale": 0.8
}